certbot_dns_dynu_dev/__init__.py
certbot_dns_dynu_dev/dns_dynu.py
certbot_dns_dynu_dev/dns_dynu_test.py
certbot_dns_dynu_dev-0.0.9.dist-info/licenses/LICENSE
certbot_dns_dynu_dev-0.0.9.dist-info/METADATA
certbot_dns_dynu_dev-0.0.9.dist-info/WHEEL
certbot_dns_dynu_dev-0.0.9.dist-info/entry_points.txt
certbot_dns_dynu_dev-0.0.9.dist-info/top_level.txt
certbot_dns_dynu_dev-0.0.9.dist-info/RECORD
