Metadata-Version: 2.4
Name: certbot-dns-dynu-dev
Version: 0.0.9
Summary: Updated Dynu DNS Authenticator plugin for Certbot
Home-page: https://github.com/BigThunderSR/certbot-dns-dynu-dev
Download-URL: https://github.com/BigThunderSR/certbot-dns-dynu-dev/archive/refs/tags/0.0.9.tar.gz
Author: Updated by BigThunderSR; original author Bikramjeet Sing,
License: Apache License 2.0
Classifier: Development Status :: 5 - Production/Stable
Classifier: Environment :: Plugins
Classifier: Intended Audience :: System Administrators
Classifier: License :: OSI Approved :: Apache Software License
Classifier: Operating System :: POSIX :: Linux
Classifier: Programming Language :: Python
Classifier: Programming Language :: Python :: 3.9
Classifier: Programming Language :: Python :: 3.10
Classifier: Programming Language :: Python :: 3.11
Classifier: Programming Language :: Python :: 3.12
Classifier: Programming Language :: Python :: 3.13
Classifier: Topic :: Internet :: WWW/HTTP
Classifier: Topic :: Security
Classifier: Topic :: System :: Installation/Setup
Classifier: Topic :: System :: Networking
Classifier: Topic :: System :: Systems Administration
Classifier: Topic :: Utilities
Requires-Python: >=3.9
License-File: LICENSE
Requires-Dist: acme>3.0.0
Requires-Dist: certbot>3.0.0
Requires-Dist: dns-lexicon>3.0.0
Requires-Dist: tldextract>=5.0.0
Requires-Dist: dnspython
Requires-Dist: mock
Requires-Dist: setuptools>=68.0.0
Requires-Dist: requests
Dynamic: author
Dynamic: classifier
Dynamic: description
Dynamic: description-content-type
Dynamic: download-url
Dynamic: home-page
Dynamic: license
Dynamic: license-file
Dynamic: requires-dist
Dynamic: requires-python
Dynamic: summary
